0_example_usage/usage_all.ipynb
0_example_usage/usage_circle-crop.ipynb
0_example_usage/usage_fovea-od_inference.ipynb
0_example_usage/usage_quality.ipynb
0_example_usage/usage_registration.ipynb
0_example_usage/usage_vessel-segmentation.ipynb
0_example_usage/training and evaluation/training_fovea-od_cli.py
0_example_usage/training and evaluation/training_quality_cli.py
1_read_more/Readmore_circle_crop.md
1_read_more/Readmore_fovea_od_localization.md
1_read_more/Readmore_quality_prediction.md
1_read_more/Readmore_registration.md
1_read_more/Readmore_utilities.md
1_read_more/Readmore_vessel_segmentation.md
fundus_image_toolbox/__init__.py
fundus_image_toolbox/circle_crop/__init__.py
fundus_image_toolbox/circle_crop/eyeq_preprocess.py
fundus_image_toolbox/fovea_od_localization/__init__.py
fundus_image_toolbox/fovea_od_localization/dataset_multi.py
fundus_image_toolbox/fovea_od_localization/default.py
fundus_image_toolbox/fovea_od_localization/model_multi.py
fundus_image_toolbox/fovea_od_localization/train_multi.py
fundus_image_toolbox/fovea_od_localization/transforms_multi.py
fundus_image_toolbox/fovea_od_localization/data/ADAM+IDRID+REFUGE_df.csv
fundus_image_toolbox/quality_prediction/__init__.py
fundus_image_toolbox/quality_prediction/scripts/__init__.py
fundus_image_toolbox/quality_prediction/scripts/dataloader.py
fundus_image_toolbox/quality_prediction/scripts/dataset.py
fundus_image_toolbox/quality_prediction/scripts/default.py
fundus_image_toolbox/quality_prediction/scripts/ensemble_inference.py
fundus_image_toolbox/quality_prediction/scripts/model.py
fundus_image_toolbox/quality_prediction/scripts/transforms.py
fundus_image_toolbox/registration/__init__.py
fundus_image_toolbox/registration/inference.py
fundus_image_toolbox/registration/SuperRetina/__init__.py
fundus_image_toolbox/registration/SuperRetina/predictor.py
fundus_image_toolbox/registration/SuperRetina/test_on_FIRE.py
fundus_image_toolbox/registration/SuperRetina/test_on_VARIA.py
fundus_image_toolbox-0.1.0.dist-info/LICENSE
fundus_image_toolbox-0.1.0.dist-info/METADATA
fundus_image_toolbox-0.1.0.dist-info/WHEEL
fundus_image_toolbox-0.1.0.dist-info/top_level.txt
fundus_image_toolbox-0.1.0.dist-info/RECORD
