Metadata-Version: 2.2
Name: fundus_image_toolbox
Version: 0.1.0
Summary: A toolbox for fundus image analysis
Author-email: Julius Gervelmeyer <Julius.Gervelmeyer@uni-tuebingen.de>
Project-URL: repository, https://github.com/berenslab/fundus_image_toolbox
Requires-Python: >=3.9
License-File: LICENSE
Requires-Dist: albumentations
Requires-Dist: captum>=0.7.0
Requires-Dist: gdown>=5.2.0
Requires-Dist: imgaug>=0.4.0
Requires-Dist: ipykernel>=6.29.5
Requires-Dist: ipython>=8.18.1
Requires-Dist: jupyter>=1.1.1
Requires-Dist: jupyter-black>=0.4.0
Requires-Dist: matplotlib>=3.6.2
Requires-Dist: matplotlib-inline>=0.1.6
Requires-Dist: munch>=4.0.0
Requires-Dist: mypy>=0.910
Requires-Dist: notebook-shim>=0.2.4
Requires-Dist: numpy>=1.24.0
Requires-Dist: opencv-python-headless>=4.9.0.80
Requires-Dist: openpyxl>=3.1.2
Requires-Dist: pandas>=1.4.2
Requires-Dist: pillow>=10.2.0
Requires-Dist: pip>=25.0
Requires-Dist: pyyaml>=6.0.0
Requires-Dist: scikit-image>=0.22.0
Requires-Dist: scikit-learn>=1.1.2
Requires-Dist: scipy>=1.10.0
Requires-Dist: seaborn>=0.13.2
Requires-Dist: timm>=0.9.16
Requires-Dist: torch>=2.2.0
Requires-Dist: torchinfo>=1.8.0
Requires-Dist: torchvision>=0.15.2
Requires-Dist: tqdm>=4.66.2
